django_multidb/__init__.py
django_multidb/models/base.py
django_multidb/models/deletion.py
django_multidb/models/fields/rel.py
django_multidb/models/query.py
django_multidb/routers.py
django_multidb-0.1.1.dist-info/LICENSE
django_multidb-0.1.1.dist-info/METADATA
django_multidb-0.1.1.dist-info/WHEEL
django_multidb-0.1.1.dist-info/RECORD
