Metadata-Version: 2.1
Name: django-multidb
Version: 0.1.1
Summary: 
Author: whc
Author-email: 249768447@qq.com
Requires-Python: >=3.10,<4.0
Classifier: Programming Language :: Python :: 3
Classifier: Programming Language :: Python :: 3.10
Classifier: Programming Language :: Python :: 3.11
Classifier: Programming Language :: Python :: 3.12
Requires-Dist: django (==4.1.13)
